geodeapp_viewer/app.py
GeodeApp_Viewer-0.2.2.dist-info/LICENSE
GeodeApp_Viewer-0.2.2.dist-info/METADATA
GeodeApp_Viewer-0.2.2.dist-info/WHEEL
GeodeApp_Viewer-0.2.2.dist-info/entry_points.txt
GeodeApp_Viewer-0.2.2.dist-info/top_level.txt
GeodeApp_Viewer-0.2.2.dist-info/RECORD
