Metadata-Version: 2.1
Name: GeodeApp-Viewer
Version: 0.2.2
Summary: GeopeApp-Viewer is the viewer microservice of the GeodeApp
Author-email: Geode-solutions <team-web@geode-solutions.com>
Project-URL: Homepage, https://github.com/Geode-solutions/GeodeApp-Viewer
Project-URL: Bug Tracker, https://github.com/Geode-solutions/GeodeApp-Viewer/issues
Classifier: Programming Language :: Python :: 3
Classifier: License :: OSI Approved :: MIT License
Classifier: Operating System :: OS Independent
Requires-Python: >=3.8
License-File: LICENSE
Requires-Dist: aiohttp ==3.9.3
Requires-Dist: aiosignal ==1.3.1
Requires-Dist: async-timeout ==4.0.3
Requires-Dist: attrs ==23.2.0
Requires-Dist: contourpy ==1.3.0
Requires-Dist: cycler ==0.12.1
Requires-Dist: fonttools ==4.54.1
Requires-Dist: frozenlist ==1.4.1
Requires-Dist: idna ==3.6
Requires-Dist: jsonschema ==4.21.1
Requires-Dist: jsonschema-specifications ==2023.12.1
Requires-Dist: kiwisolver ==1.4.7
Requires-Dist: matplotlib ==3.9.2
Requires-Dist: multidict ==6.0.5
Requires-Dist: numpy ==2.1.2
Requires-Dist: opengeodeweb-viewer[gpu] ==0.2.1
Requires-Dist: packaging ==24.1
Requires-Dist: pillow ==11.0.0
Requires-Dist: pyparsing ==3.2.0
Requires-Dist: python-dateutil ==2.9.0.post0
Requires-Dist: python-dotenv ==1.0.1
Requires-Dist: referencing ==0.33.0
Requires-Dist: rpds-py ==0.18.0
Requires-Dist: six ==1.16.0
Requires-Dist: vtk ==9.3.1
Requires-Dist: websocket-client ==1.7.0
Requires-Dist: wslink ==1.12.4
Requires-Dist: yarl ==1.9.4
Provides-Extra: gpu
Requires-Dist: vtk ==9.* ; extra == 'gpu'
